setup.py
dockerrotate/__init__.py
dockerrotate/containers.py
dockerrotate/filter.py
dockerrotate/images.py
dockerrotate/main.py
dockerrotate/untagged.py
dockerrotate.egg-info/PKG-INFO
dockerrotate.egg-info/SOURCES.txt
dockerrotate.egg-info/dependency_links.txt
dockerrotate.egg-info/entry_points.txt
dockerrotate.egg-info/requires.txt
dockerrotate.egg-info/top_level.txt