Metadata-Version: 1.0
Name: dockerrotate
Version: 3.1
Summary: Docker image rotation tool
Home-page: http://locationlabs.com
Author: Location Labs
Author-email: info@locationlabs.com
License: UNKNOWN
Platform: UNKNOWN
